<?xml version="1.0" encoding="utf-8" ?>
<ArrayOfTrivialType xmlns:xsi="http://www.w3.org/2001/XMLSchema-instance"
                    xmlns:xsd="http://www.w3.org/2001/XMLSchema">
    <TrivialType xsi:type="RegexMatch"
                 RegexString="^System\.String" />
    <TrivialType xsi:type="RegexMatch"
                 RegexString="^System\.Char" />
    <TrivialType xsi:type="ExactMatch"
                 FullTypeName="System.Type" />
    <TrivialType xsi:type="ExactMatch"
                 FullTypeName="System.Int32" />
    <TrivialType xsi:type="RegexMatch"
                 RegexString="^System\.Action" />
    <TrivialType xsi:type="ExactMatch"
                 FullTypeName="System.Boolean" />
    <TrivialType xsi:type="RegexMatch"
                 RegexString="^System\.EventHandler" />
    <TrivialType xsi:type="RegexMatch"
                 RegexString="^System\.Collections" />
    <TrivialType xsi:type="RegexMatch"
                 RegexString="^System\.Object" />
    <TrivialType xsi:type="RegexMatch"
                 RegexString="^System\.Nullable" />
    <TrivialType xsi:type="RegexMatch"
                 RegexString="^System\.Func" />
    <TrivialType xsi:type="RegexMatch"
                 RegexString="^System\.Action" />
    <TrivialType xsi:type="RegexMatch"
                 RegexString="^System\.DateTime" />
    <TrivialType xsi:type="RegexMatch"
                 RegexString="^System\.UInt" />
    <TrivialType xsi:type="RegexMatch"
                 RegexString="^System\.Text\." />
    <TrivialType xsi:type="ExactMatch"
                 FullTypeName="System.Threading.Interlocked" />
    <TrivialType xsi:type="ExactMatch"
                 FullTypeName="System.Delegate" />
</ArrayOfTrivialType>